requests_hustauth/__init__.py
requests_hustauth/requests_hustauth.py
requests_hustauth/data/ref_digits_data.npz
requests_hustauth-1.0.1.dist-info/LICENSE
requests_hustauth-1.0.1.dist-info/METADATA
requests_hustauth-1.0.1.dist-info/WHEEL
requests_hustauth-1.0.1.dist-info/top_level.txt
requests_hustauth-1.0.1.dist-info/RECORD
