Metadata-Version: 2.1
Name: requests_hustauth
Version: 1.0.1
Summary: HustPass support for Python-Requests
Home-page: https://github.com/MarvinTerry/HustAuth
Author: MarvinTerry
Author-email: marvinterry2004@gmail.com
License: MIT
Classifier: Programming Language :: Python :: 3
Classifier: License :: OSI Approved :: MIT License
Classifier: Operating System :: OS Independent
License-File: LICENSE
Requires-Dist: fake-useragent >=1.2.0
Requires-Dist: Pillow >=10.0.0
Requires-Dist: pycryptodome >=3.18.0
Requires-Dist: Requests >=2.31.0
Requires-Dist: numpy
Requires-Dist: setuptools
